codechat/__init__.py
codechat/__main__.py
codez_cli-0.2.0.dist-info/licenses/LICENSE
core/__init__.py
core/context_manager.py
core/llm_interactive.py
core/llm_interactive_demo.py
core/model.py
core/parser.py
core/repl.py
core/sqlite_memory.py
core/stream_utils.py
core/summarizer.py
core/user_config.py
codez_cli-0.2.0.dist-info/METADATA
codez_cli-0.2.0.dist-info/WHEEL
codez_cli-0.2.0.dist-info/entry_points.txt
codez_cli-0.2.0.dist-info/top_level.txt
codez_cli-0.2.0.dist-info/RECORD
