Metadata-Version: 2.4
Name: codez-cli
Version: 0.2.0
Summary: CodeZ CLI – Your Offline Code Companion
Home-page: https://github.com/sam43/code-z-cli
Author: Sadat Sayem
Author-email: Sadat Sayem <scode43@gmail.com>
Requires-Python: >=3.8
License-File: LICENSE
Requires-Dist: rich
Requires-Dist: prompt_toolkit
Requires-Dist: platformdirs
Requires-Dist: tree-sitter
Dynamic: author
Dynamic: home-page
Dynamic: license-file
Dynamic: requires-python
